rpps/__init__.py
rpps/dobject.py
rpps/file.py
rpps/meta.py
rpps/base/__bitarray.py
rpps/base/__init__.py
rpps/base/__stream.py
rpps/base/_meta.py
rpps/base/frequency.py
rpps/base/rpps.py
rpps/base/soft.py
rpps/coding/__init__.py
rpps/coding/_identify.py
rpps/coding/coding.py
rpps/coding/meta.py
rpps/coding/_blk/__init__.py
rpps/coding/_blk/repetition.py
rpps/coding/_cnv/__init__.py
rpps/coding/_cnv/viterbi.py
rpps/freq/__init__.py
rpps/freq/meta.py
rpps/helpers/__init__.py
rpps/helpers/args.py
rpps/helpers/binary.py
rpps/helpers/formats.py
rpps/inter/__init__.py
rpps/inter/file.py
rpps/inter/interface.py
rpps/inter/meta.py
rpps/mod/__init__.py
rpps/mod/constellation.py
rpps/mod/meta.py
rpps/mod/modulation.py
rpps/mod/serial.py
rpps/process/__init__.py
rpps/process/rate.py
rpps/viz/__init__.py
rpps/viz/dialog.py
rpps/viz/freq.py
rpps/viz/generic.py
rpps/viz/time.py
rpps-0.1.0.dist-info/LICENSE
rpps-0.1.0.dist-info/METADATA
rpps-0.1.0.dist-info/WHEEL
rpps-0.1.0.dist-info/top_level.txt
rpps-0.1.0.dist-info/RECORD
