Metadata-Version: 2.1
Name: rpps
Version: 0.1.0
Summary: RF Parameter Processor Suite
Author-email: Anonoei <dev@anonoei.com>
Project-URL: Homepage, https://github.com/anonoei/RPPS
Project-URL: Documentation, https://anonoei.github.io/RPPS/
Project-URL: Repository, https://github.com/Anonoei/RPPS.git
Project-URL: Issues, https://github.com/Anonoei/RPPS/issues
Project-URL: Source, https://github.com/anonoei/RPPS
Keywords: anonoei,dsp,sdr
Classifier: Development Status :: 4 - Beta
Classifier: Intended Audience :: Developers
Classifier: License :: OSI Approved :: MIT License
Classifier: Programming Language :: Python :: 3
Classifier: Operating System :: OS Independent
Requires-Python: >=3.6
License-File: LICENSE
Requires-Dist: pyboiler-anonoei
Requires-Dist: numpy
Requires-Dist: matplotlib
Provides-Extra: dev
Requires-Dist: twine ; extra == 'dev'
Requires-Dist: build ; extra == 'dev'
Requires-Dist: bumpver ; extra == 'dev'
Requires-Dist: pytest ; extra == 'dev'
Requires-Dist: pdoc3 ; extra == 'dev'
